analysis/__init__.py
analysis/correlation.py
analysis/timeMotif.py
helpers/__init__.py
helpers/analysis.py
helpers/input.py
helpers/timeseries.py
input/FSDB.py
input/__init__.py
output/DF.py
output/__init__.py
output/timeMotifGraph.py
util/__init__.py
util/util.py
ts_analysis-0.0.3.dist-info/LICENSE.txt
ts_analysis-0.0.3.dist-info/METADATA
ts_analysis-0.0.3.dist-info/WHEEL
ts_analysis-0.0.3.dist-info/entry_points.txt
ts_analysis-0.0.3.dist-info/top_level.txt
ts_analysis-0.0.3.dist-info/RECORD
