Metadata-Version: 2.1
Name: ts-analysis
Version: 0.0.3
Summary: Scripts to find reoccuring patterns in time series.
Home-page: https://git.ant.isi.edu/GAWSEED
Author: Genevieve Bartlett, USC/ISI
Author-email: bartlett@isi.edu
License: UNKNOWN
Keywords: time series network events time motif motifs signal processing fsdb
Platform: UNKNOWN
Classifier: Development Status :: 3 - Alpha
Classifier: Intended Audience :: Developers
Classifier: Topic :: Software Development :: Build Tools
Classifier: License :: OSI Approved :: MIT License
Classifier: Programming Language :: Python :: 3.6
Classifier: Programming Language :: Python :: 3.7
Classifier: Programming Language :: Python :: 3.8
Requires-Python: >=3.6
Requires-Dist: pandas (>=0.25.0)
Requires-Dist: matplotlib (>=3.1.2)
Requires-Dist: matrixprofile-ts (==0.0.8)
Requires-Dist: pyfsdb (>=1.1.19)
Requires-Dist: scipy (>=1.6.0)
Requires-Dist: numpy (>=1.19.5)
Provides-Extra: dev
Requires-Dist: check-manifest ; extra == 'dev'
Provides-Extra: test
Requires-Dist: coverage ; extra == 'test'
